{
  "ogmoVersion": "3.4.0",
  "width": 640,
  "height": 480,
  "offsetX": 0,
  "offsetY": 0,
  "layers": [
    {
      "name": "entities ",
      "_eid": "44153784",
      "offsetX": 0,
      "offsetY": 0,
      "gridCellWidth": 8,
      "gridCellHeight": 8,
      "gridCellsX": 80,
      "gridCellsY": 60,
      "entities": [
        {"name": "Sonic/Player", "id": 0, "_eid": "44136032", "x": 64, "y": 272, "originX": 0, "originY": 0}
      ]
    },
    {
      "name": "floorz",
      "_eid": "44158443",
      "offsetX": 0,
      "offsetY": 0,
      "gridCellWidth": 8,
      "gridCellHeight": 8,
      "gridCellsX": 80,
      "gridCellsY": 60,
      "tileset": "GHZ",
      "data": [-1, -1, -1, -1, -1, -1, 56, -1, -1, -1, -1, -1, -1, -1, -1, -1, -1, -1, -1, -1, -1, -1, -1, -1, -1, -1, -1, -1, -1, -1, -1, -1, -1, -1, -1, -1, -1, -1, -1, -1, -1, -1, -1, -1, -1, -1, -1, -1, -1, -1, -1, -1, -1, -1, -1, -1, -1, -1, -1, -1, -1, -1, -1, -1, -1, -1, -1, -1, -1, -1, -1, -1, 56, -1, -1, -1, -1, -1, -1, -1, -1, -1, -1, -1, -1, -1, 56, -1, -1, -1, -1, -1, -1, -1, -1, -1, -1, -1, -1, -1, -1, -1, -1, -1, -1, -1, -1, -1, -1, -1, -1, -1, -1, -1, -1, -1, -1, -1, -1, -1, -1, -1, -1, -1, -1, -1, -1, -1, -1, -1, -1, -1, -1, -1, -1, -1, -1, -1, -1, -1, -1, -1, -1, -1, -1, -1, -1, -1, -1, -1, -1, -1, 56, -1, -1, -1, -1, -1, -1, -1, -1, -1, -1, -1, -1, -1, 56, -1, -1, -1, -1, -1, -1, -1, -1, -1, -1, -1, -1, -1, -1, -1, -1, -1, -1, -1, -1, -1, -1, -1, -1, -1, -1, -1, -1, -1, -1, -1, -1, -1, -1, -1, -1, -1, -1, -1, -1, -1, -1, -1, -1, -1, -1, -1, -1, -1, -1, -1, -1, -1, -1, -1, -1, -1, -1, -1, -1, -1, -1, -1, -1, -1, 56, -1, -1, -1, -1, -1, -1, -1, -1, -1, -1, -1, -1, -1, 56, -1, -1, -1, -1, -1, -1, -1, -1, -1, -1, -1, -1, -1, -1, -1, -1, -1, -1, -1, -1, -1, -1, -1, -1, -1, -1, -1, -1, -1, -1, -1, -1, -1, -1, -1, -1, -1, -1, -1, -1, -1, -1, -1, -1, -1, -1, -1, -1, -1, -1, -1, -1, -1, -1, -1, -1, -1, -1, -1, -1, -1, -1, -1, -1, -1, 56, -1, -1, -1, -1, -1, -1, -1, -1, -1, -1, -1, -1, -1, 56, -1, -1, -1, -1, -1, -1, -1, -1, -1, -1, -1, -1, -1, -1, -1, -1, -1, -1, -1, -1, -1, -1, -1, -1, -1, -1, -1, -1, -1, -1, -1, -1, -1, -1, -1, -1, -1, -1, -1, -1, -1, -1, -1, -1, -1, -1, -1, -1, -1, -1, -1, -1, -1, -1, -1, -1, -1, -1, -1, -1, -1, -1, -1, -1, -1, 56, -1, -1, -1, -1, -1, -1, -1, -1, -1, -1, -1, -1, -1, 56, -1, -1, -1, -1, -1, -1, -1, -1, -1, -1, -1, -1, -1, -1, -1, -1, -1, -1, -1, -1, -1, -1, -1, -1, -1, -1, -1, -1, -1, -1, -1, -1, -1, -1, -1, -1, -1, -1, -1, -1, -1, -1, -1, -1, -1, -1, -1, -1, -1, -1, -1, -1, -1, -1, -1, -1, -1, -1, -1, -1, -1, -1, -1, -1, -1, 56, -1, -1, -1, -1, -1, -1, -1, -1, -1, -1, -1, -1, -1, 56, -1, -1, -1, -1, -1, -1, -1, -1, -1, -1, -1, -1, -1, -1, -1, -1, -1, -1, -1, -1, -1, -1, -1, -1, -1, -1, -1, -1, -1, -1, -1, -1, -1, -1, -1, -1, -1, -1, -1, -1, -1, -1, -1, -1, -1, -1, -1, -1, -1, -1, -1, -1, -1, -1, -1, -1, -1, -1, -1, -1, -1, -1, -1, -1, -1, 56, -1, -1, -1, -1, -1, -1, -1, -1, -1, -1, -1, -1, -1, 56, -1, -1, -1, -1, -1, -1, -1, -1, -1, -1, -1, -1, -1, -1, -1, -1, -1, -1, -1, -1, -1, -1, -1, -1, -1, -1, -1, -1, -1, -1, -1, -1, -1, -1, -1, -1, -1, -1, -1, -1, -1, -1, -1, -1, -1, -1, -1, -1, -1, -1, -1, -1, -1, -1, -1, -1, -1, -1, -1, -1, -1, -1, -1, -1, -1, 56, -1, -1, -1, -1, -1, -1, -1, -1, -1, -1, -1, -1, -1, 56, -1, -1, -1, -1, -1, -1, -1, -1, -1, -1, -1, -1, -1, -1, -1, -1, -1, -1, -1, -1, -1, -1, -1, -1, -1, -1, -1, -1, -1, -1, -1, -1, -1, -1, -1, -1, -1, -1, -1, -1, -1, -1, -1, -1, -1, -1, -1, -1, -1, -1, -1, -1, -1, -1, -1, -1, -1, -1, -1, -1, -1, -1, -1, -1, -1, 56, -1, -1, -1, -1, -1, -1, -1, -1, -1, -1, -1, -1, -1, 56, -1, -1, -1, -1, -1, -1, -1, -1, -1, -1, -1, -1, -1, -1, -1, -1, -1, -1, -1, -1, -1, -1, -1, -1, -1, -1, -1, -1, -1, -1, -1, -1, -1, -1, -1, -1, -1, -1, -1, -1, -1, -1, -1, -1, -1, -1, -1, -1, -1, -1, -1, -1, -1, -1, -1, -1, -1, -1, -1, -1, -1, -1, -1, -1, -1, 56, -1, -1, -1, -1, -1, -1, -1, -1, -1, -1, -1, -1, -1, 56, -1, -1, -1, -1, -1, -1, -1, -1, -1, -1, -1, -1, -1, -1, -1, -1, -1, -1, -1, -1, -1, -1, -1, -1, -1, -1, -1, -1, -1, -1, -1, -1, -1, -1, -1, -1, -1, -1, -1, -1, -1, -1, -1, -1, -1, -1, -1, -1, -1, -1, -1, -1, -1, -1, -1, -1, -1, -1, -1, -1, -1, -1, -1, -1, -1, 56, -1, -1, -1, -1, -1, -1, -1, -1, -1, -1, -1, -1, -1, 56, -1, -1, -1, -1, -1, -1, -1, -1, -1, -1, -1, -1, -1, -1, -1, -1, -1, -1, -1, -1, -1, -1, -1, -1, -1, -1, -1, -1, -1, -1, -1, -1, -1, -1, -1, -1, -1, -1, -1, -1, -1, -1, -1, -1, -1, -1, -1, -1, -1, -1, -1, -1, -1, -1, -1, -1, -1, -1, -1, -1, -1, -1, -1, -1, -1, 56, -1, -1, -1, -1, -1, -1, -1, -1, -1, -1, -1, -1, -1, 56, -1, -1, -1, -1, -1, -1, -1, -1, -1, -1, -1, -1, -1, -1, -1, -1, -1, -1, -1, -1, -1, -1, -1, -1, -1, -1, -1, -1, -1, -1, -1, -1, -1, -1, -1, -1, -1, -1, -1, -1, -1, -1, -1, -1, -1, -1, -1, -1, -1, -1, -1, -1, -1, -1, -1, -1, -1, -1, -1, -1, -1, -1, -1, -1, -1, 56, -1, -1, -1, -1, -1, -1, -1, -1, -1, -1, -1, -1, -1, 56, -1, -1, -1, -1, -1, -1, -1, -1, -1, -1, -1, -1, -1, -1, -1, -1, -1, -1, -1, -1, -1, -1, -1, -1, -1, -1, -1, -1, -1, -1, -1, -1, -1, -1, -1, -1, -1, -1, -1, -1, -1, -1, -1, -1, -1, -1, -1, -1, -1, -1, -1, -1, -1, -1, -1, -1, -1, -1, -1, -1, -1, -1, -1, -1, -1, 56, -1, -1, -1, -1, -1, -1, -1, -1, -1, -1, -1, -1, -1, 56, -1, -1, -1, -1, -1, -1, -1, -1, -1, -1, -1, -1, -1, -1, -1, -1, -1, -1, -1, -1, -1, -1, -1, -1, -1, -1, -1, -1, -1, -1, -1, -1, -1, -1, -1, -1, -1, -1, -1, -1, -1, -1, -1, -1, -1, -1, -1, -1, -1, -1, -1, -1, -1, -1, -1, -1, -1, -1, -1, -1, -1, -1, -1, -1, -1, 56, -1, -1, -1, -1, -1, -1, -1, -1, -1, -1, -1, -1, -1, 56, -1, -1, -1, -1, -1, -1, -1, -1, -1, -1, -1, -1, -1, -1, -1, -1, -1, -1, -1, -1, -1, -1, -1, -1, -1, -1, -1, -1, -1, -1, -1, -1, -1, -1, -1, -1, -1, -1, -1, -1, -1, -1, -1, -1, -1, -1, -1, -1, -1, -1, -1, -1, -1, -1, -1, -1, -1, -1, -1, -1, -1, -1, -1, -1, -1, 56, -1, -1, -1, -1, -1, -1, -1, -1, -1, -1, -1, -1, -1, 56, -1, -1, -1, -1, -1, -1, -1, -1, -1, -1, -1, -1, -1, -1, -1, -1, -1, -1, -1, -1, -1, -1, -1, -1, -1, -1, -1, -1, -1, -1, -1, -1, -1, -1, -1, -1, -1, -1, -1, -1, -1, -1, -1, -1, -1, -1, -1, -1, -1, -1, -1, -1, -1, -1, -1, -1, -1, -1, -1, -1, -1, -1, -1, -1, -1, 56, -1, -1, -1, -1, -1, -1, -1, -1, -1, -1, -1, -1, -1, 56, -1, -1, -1, -1, -1, -1, -1, -1, -1, -1, -1, -1, -1, -1, -1, -1, -1, -1, -1, -1, -1, -1, -1, -1, -1, -1, -1, -1, -1, -1, -1, -1, -1, -1, -1, -1, -1, -1, -1, -1, -1, -1, -1, -1, -1, -1, -1, -1, -1, -1, -1, -1, -1, -1, -1, -1, -1, -1, -1, -1, -1, -1, -1, -1, -1, 56, -1, -1, -1, -1, -1, -1, -1, -1, -1, -1, -1, -1, -1, 56, -1, -1, -1, -1, -1, -1, -1, -1, -1, -1, -1, -1, -1, -1, -1, -1, -1, -1, -1, -1, -1, -1, -1, -1, -1, -1, -1, -1, -1, -1, -1, -1, -1, -1, -1, -1, -1, -1, -1, -1, -1, -1, -1, -1, -1, -1, -1, -1, -1, -1, -1, -1, -1, -1, -1, -1, -1, -1, -1, -1, -1, -1, -1, -1, -1, 56, -1, -1, -1, -1, -1, -1, -1, -1, -1, -1, -1, -1, -1, 56, -1, -1, -1, -1, -1, -1, -1, -1, -1, -1, -1, -1, -1, -1, -1, -1, -1, -1, -1, -1, -1, -1, -1, -1, -1, -1, -1, -1, -1, -1, -1, -1, -1, -1, -1, -1, -1, -1, -1, -1, -1, -1, -1, -1, -1, -1, -1, -1, -1, -1, -1, -1, -1, -1, -1, -1, -1, -1, -1, -1, -1, -1, -1, -1, -1, 56, -1, -1, -1, -1, -1, -1, -1, -1, -1, -1, -1, -1, -1, 56, -1, -1, -1, -1, -1, -1, -1, -1, -1, -1, -1, -1, -1, -1, -1, -1, -1, -1, -1, -1, -1, -1, -1, -1, -1, -1, -1, -1, -1, -1, -1, -1, -1, -1, -1, -1, -1, -1, -1, -1, -1, -1, -1, -1, -1, -1, -1, -1, -1, -1, -1, -1, -1, -1, -1, -1, -1, -1, -1, -1, -1, -1, -1, -1, -1, 56, -1, -1, -1, -1, -1, -1, -1, -1, -1, -1, -1, -1, -1, 56, -1, -1, -1, -1, -1, -1, -1, -1, -1, -1, -1, -1, -1, -1, -1, -1, -1, -1, -1, -1, -1, -1, -1, -1, -1, -1, -1, -1, -1, -1, -1, -1, -1, -1, -1, -1, -1, -1, -1, -1, -1, -1, -1, -1, -1, -1, -1, -1, -1, -1, -1, -1, -1, -1, -1, -1, -1, -1, -1, -1, -1, -1, -1, -1, -1, 56, -1, -1, -1, -1, -1, -1, -1, -1, -1, -1, -1, -1, -1, 56, -1, -1, -1, -1, -1, -1, -1, -1, -1, -1, -1, -1, -1, -1, -1, -1, -1, -1, -1, -1, -1, -1, -1, -1, -1, -1, -1, -1, -1, -1, -1, -1, -1, -1, -1, -1, -1, -1, -1, -1, -1, -1, -1, -1, -1, -1, -1, -1, -1, -1, -1, -1, -1, -1, -1, -1, -1, -1, -1, -1, -1, -1, -1, -1, -1, 56, -1, -1, -1, -1, -1, -1, -1, -1, -1, -1, -1, -1, -1, 56, -1, -1, -1, -1, -1, -1, -1, -1, -1, -1, -1, -1, -1, -1, -1, -1, -1, -1, -1, -1, -1, -1, -1, -1, -1, -1, -1, -1, -1, -1, -1, -1, -1, -1, -1, -1, -1, -1, -1, -1, -1, -1, -1, -1, -1, -1, -1, -1, -1, -1, -1, -1, -1, -1, -1, -1, -1, -1, -1, -1, -1, -1, -1, -1, -1, 56, -1, -1, -1, -1, -1, -1, -1, -1, -1, -1, -1, -1, -1, 56, -1, -1, -1, -1, -1, -1, -1, -1, -1, -1, -1, -1, -1, -1, -1, -1, -1, -1, -1, -1, -1, -1, -1, -1, -1, -1, -1, -1, -1, -1, -1, -1, -1, -1, -1, -1, -1, -1, -1, -1, -1, -1, -1, -1, -1, -1, -1, -1, -1, -1, -1, -1, -1, -1, -1, -1, -1, -1, -1, -1, -1, -1, -1, -1, -1, 56, -1, -1, -1, -1, -1, -1, -1, -1, -1, -1, -1, -1, -1, 56, 56, -1, -1, -1, -1, -1, -1, -1, -1, -1, -1, -1, -1, -1, -1, -1, -1, -1, -1, -1, -1, -1, -1, -1, -1, -1, -1, -1, -1, -1, -1, -1, -1, -1, -1, -1, -1, -1, -1, -1, -1, -1, -1, -1, -1, -1, -1, -1, -1, -1, -1, -1, -1, -1, -1, -1, -1, -1, -1, -1, -1, -1, -1, -1, -1, 56, -1, -1, -1, -1, -1, -1, -1, -1, -1, -1, -1, -1, -1, -1, 56, -1, -1, -1, -1, -1, -1, -1, -1, -1, -1, -1, -1, -1, -1, -1, -1, -1, -1, -1, -1, -1, -1, -1, -1, -1, -1, -1, -1, -1, -1, -1, -1, -1, -1, -1, -1, -1, -1, -1, -1, -1, -1, -1, -1, -1, -1, -1, -1, -1, -1, -1, -1, -1, -1, -1, -1, -1, -1, -1, -1, -1, -1, -1, -1, 56, -1, -1, -1, -1, -1, -1, -1, -1, -1, -1, -1, -1, -1, 56, -1, -1, -1, -1, -1, -1, -1, -1, -1, -1, -1, -1, -1, -1, -1, -1, -1, -1, -1, -1, -1, -1, -1, -1, -1, -1, -1, -1, -1, -1, -1, -1, -1, -1, -1, -1, -1, -1, -1, -1, -1, -1, -1, -1, -1, -1, -1, -1, -1, -1, -1, -1, -1, -1, -1, -1, -1, -1, -1, -1, -1, -1, -1, -1, -1, 56, -1, -1, -1, -1, -1, -1, -1, -1, -1, -1, -1, -1, -1, 56, -1, -1, -1, -1, -1, -1, -1, -1, -1, -1, -1, -1, -1, -1, -1, -1, -1, -1, -1, -1, -1, -1, -1, -1, -1, -1, -1, -1, -1, -1, -1, -1, -1, -1, -1, -1, -1, -1, -1, -1, -1, -1, -1, -1, -1, -1, -1, -1, -1, -1, -1, -1, -1, -1, -1, -1, -1, -1, -1, -1, -1, -1, -1, -1, -1, 56, -1, -1, -1, -1, -1, -1, -1, -1, -1, -1, -1, -1, -1, 56, -1, -1, -1, -1, -1, -1, -1, -1, -1, -1, -1, -1, -1, -1, -1, -1, -1, -1, -1, -1, -1, -1, -1, -1, -1, -1, -1, -1, -1, -1, -1, -1, -1, -1, -1, -1, -1, -1, -1, -1, -1, -1, -1, -1, -1, -1, -1, -1, -1, -1, -1, -1, -1, -1, -1, -1, -1, -1, -1, -1, -1, -1, -1, -1, -1, 56, -1, -1, -1, -1, -1, -1, -1, -1, -1, -1, -1, -1, -1, 56, -1, -1, -1, -1, -1, -1, -1, -1, -1, -1, -1, -1, -1, -1, -1, -1, -1, -1, -1, -1, -1, -1, -1, -1, -1, -1, -1, -1, -1, -1, -1, -1, -1, -1, -1, -1, -1, -1, -1, -1, -1, -1, -1, -1, -1, -1, -1, -1, -1, -1, -1, -1, -1, -1, -1, -1, -1, -1, -1, -1, -1, -1, -1, -1, -1, 56, -1, -1, -1, -1, -1, -1, -1, -1, -1, -1, -1, -1, -1, 56, -1, -1, -1, -1, -1, -1, -1, -1, -1, -1, -1, -1, -1, -1, -1, -1, -1, -1, -1, -1, -1, -1, -1, -1, -1, -1, -1, -1, -1, -1, -1, -1, -1, -1, -1, -1, -1, -1, -1, -1, -1, -1, -1, -1, -1, -1, -1, -1, -1, -1, -1, -1, -1, -1, -1, -1, -1, -1, -1, -1, -1, -1, -1, -1, -1, 56, -1, -1, -1, -1, -1, -1, -1, -1, -1, -1, -1, -1, -1, 56, -1, -1, -1, -1, -1, -1, -1, -1, -1, -1, -1, -1, -1, -1, -1, -1, -1, -1, -1, -1, -1, -1, -1, -1, -1, -1, -1, -1, -1, -1, -1, -1, -1, -1, -1, -1, -1, -1, -1, -1, -1, -1, -1, -1, -1, -1, -1, -1, -1, -1, -1, -1, -1, -1, -1, -1, -1, -1, -1, -1, -1, -1, -1, -1, -1, 56, -1, -1, -1, -1, -1, -1, -1, -1, -1, -1, -1, -1, -1, 56, -1, -1, -1, -1, -1, -1, -1, -1, -1, -1, -1, -1, -1, -1, -1, -1, -1, -1, -1, -1, -1, -1, -1, -1, -1, -1, -1, -1, -1, -1, -1, -1, -1, -1, -1, -1, -1, -1, -1, -1, -1, -1, -1, -1, -1, -1, -1, -1, -1, -1, -1, -1, -1, -1, -1, -1, -1, -1, -1, -1, -1, -1, -1, -1, -1, 56, -1, -1, -1, -1, -1, -1, -1, -1, -1, -1, -1, -1, -1, 56, -1, -1, -1, -1, -1, -1, -1, -1, -1, -1, -1, -1, -1, -1, -1, -1, -1, -1, -1, -1, -1, -1, -1, -1, -1, -1, -1, -1, -1, -1, -1, -1, -1, -1, -1, -1, -1, -1, -1, -1, -1, -1, -1, -1, -1, -1, -1, -1, -1, -1, -1, -1, -1, -1, -1, -1, -1, -1, -1, -1, -1, -1, -1, -1, -1, 56, -1, -1, -1, -1, -1, -1, -1, -1, -1, -1, -1, -1, -1, 56, -1, -1, -1, -1, -1, -1, -1, -1, -1, -1, -1, -1, -1, -1, -1, -1, -1, -1, -1, -1, -1, -1, -1, -1, -1, -1, -1, -1, -1, -1, -1, -1, -1, -1, -1, -1, -1, -1, -1, -1, -1, -1, -1, -1, -1, -1, -1, -1, -1, -1, -1, -1, -1, -1, -1, -1, -1, -1, -1, -1, -1, -1, -1, -1, -1, 56, -1, -1, -1, -1, -1, -1, -1, -1, -1, -1, -1, -1, -1, 56, -1, -1, -1, -1, -1, -1, -1, -1, -1, -1, -1, -1, -1, -1, -1, -1, -1, -1, -1, -1, -1, -1, -1, -1, -1, -1, -1, -1, -1, -1, -1, -1, -1, -1, -1, -1, -1, -1, -1, -1, -1, -1, -1, -1, -1, -1, -1, -1, -1, -1, -1, -1, -1, -1, -1, -1, -1, -1, -1, -1, -1, -1, -1, -1, -1, 56, -1, -1, -1, -1, -1, -1, -1, -1, -1, -1, -1, -1, -1, -1, -1, -1, -1, -1, -1, -1, -1, -1, -1, -1, -1, -1, -1, -1, -1, -1, -1, -1, -1, -1, -1, -1, -1, -1, -1, -1, -1, -1, -1, -1, -1, -1, -1, -1, -1, -1, -1, -1, -1, -1, -1, -1, -1, -1, -1, -1, -1, -1, -1, -1, -1, -1, -1, -1, -1, -1, -1, -1, -1, -1, -1, -1, -1, -1, -1, 56, -1, -1, -1, -1, -1, -1, -1, -1, -1, -1, -1, -1, -1, 0, 1, 2, 3, 4, 5, 6, 7, -1, 0, 1, 2, 3, 4, 5, 6, 7, -1, 0, 1, 2, 3, 4, 5, 6, 7, -1, 0, 1, 2, 3, 4, 5, 6, 7, -1, 0, 1, 2, 3, 4, 5, 6, 7, -1, 0, 1, 2, 3, 4, 5, 6, 7, -1, 0, 1, 2, 3, 4, 5, 6, 7, -1, 0, 1, 2, 3, 4, 5, 6, 7, -1, -1, -1, -1, -1, -1, -1, -1, -1, 8, 9, 10, 11, 12, 13, 14, 15, -1, 8, 9, 10, 11, 12, 13, 14, 15, -1, 8, 9, 10, 11, 12, 13, 14, 15, -1, 8, 9, 10, 11, 12, 13, 14, 15, -1, 8, 9, 10, 11, 12, 13, 14, 15, -1, 8, 9, 10, 11, 12, 13, 14, 15, -1, 8, 9, 10, 11, 12, 13, 14, 15, -1, 8, 9, 10, 11, 12, 13, 14, 15, -1, -1, -1, -1, -1, -1, -1, -1, -1, -1, -1, -1, -1, -1, -1, -1, -1, -1, -1, -1, -1, -1, -1, -1, -1, -1, -1, -1, -1, -1, -1, -1, -1, -1, -1, -1, -1, -1, -1, 17, 18, 19, 20, 21, 22, 23, -1, -1, -1, -1, -1, -1, -1, -1, -1, -1, -1, -1, -1, -1, -1, -1, -1, -1, -1, -1, -1, -1, -1, -1, -1, -1, -1, -1, -1, -1, -1, -1, -1, -1, -1, -1, -1, -1, -1, -1, -1, -1, -1, 17, 18, 19, 20, 21, 22, 23, -1, 17, 18, 19, 20, 21, 22, 23, 17, 18, 19, 20, 21, 22, 23, -1, 17, 18, 19, 20, 21, 22, 23, 25, 26, 27, 28, 29, 30, 31, 17, 18, 19, 20, 21, 22, 23, 17, 18, 19, 20, 21, 22, 23, 17, 18, 19, 20, 21, 22, 23, 17, 18, 19, 20, 21, 22, 17, 18, 19, 20, 21, 22, 23, 22, 23, -1, -1, -1, -1, -1, -1, -1, 25, 26, 27, 28, 29, 30, 31, -1, 25, 26, 27, 28, 29, 30, 31, 25, 26, 27, 28, 29, 30, 31, 17, 25, 26, 27, 28, 29, 30, 31, 33, 34, 35, 36, 37, 38, 39, 25, 26, 27, 28, 29, 30, 31, 25, 26, 27, 28, 29, 30, 31, 25, 26, 27, 28, 29, 30, 31, 25, 26, 27, 28, 29, 30, 25, 26, 27, 28, 29, 30, 31, 30, 31, -1, -1, -1, -1, -1, -1, -1, 33, 34, 35, 36, 37, 38, 39, -1, 33, 34, 35, 36, 37, 38, 39, 33, 34, 35, 36, 37, 38, 39, 25, 33, 34, 35, 36, 37, 38, 39, 41, 42, 43, 44, 45, 46, 47, 33, 34, 35, 36, 37, 38, 39, 33, 34, 35, 36, 37, 38, 39, 33, 34, 35, 36, 37, 38, 39, 33, 34, 35, 36, 37, 38, 33, 34, 35, 36, 37, 38, 39, 38, 39, -1, -1, -1, -1, -1, -1, -1, 41, 42, 43, 44, 45, 46, 47, -1, 41, 42, 43, 44, 45, 46, 47, 41, 42, 43, 44, 45, 46, 47, 33, 41, 42, 43, 44, 45, 46, 47, 49, 50, 51, 52, 53, 54, 55, 41, 42, 43, 44, 45, 46, 47, 41, 42, 43, 44, 45, 46, 47, 41, 42, 43, 44, 45, 46, 47, 41, 42, 43, 44, 45, 46, 41, 42, 43, 44, 45, 46, 47, 46, 47, -1, -1, -1, -1, -1, -1, -1, 49, 50, 51, 52, 53, 54, 55, -1, 49, 50, 51, 52, 53, 54, 55, 49, 50, 51, 52, 53, 54, 55, 41, 49, 50, 51, 52, 53, 54, 55, 57, 58, 59, 60, 61, 62, 63, 49, 50, 51, 52, 53, 54, 55, 49, 50, 51, 52, 53, 54, 55, 49, 50, 51, 52, 53, 54, 55, 49, 50, 51, 52, 53, 54, 49, 50, 51, 52, 53, 54, 55, 54, 55, -1, -1, -1, -1, -1, -1, -1, 57, 58, 59, 60, 61, 62, 63, -1, 57, 58, 59, 60, 61, 62, 63, 57, 58, 59, 60, 61, 62, 63, 49, 57, 58, 59, 60, 61, 62, 63, 50, 51, 52, 53, 54, 55, -1, 57, 58, 59, 60, 61, 62, 63, 57, 58, 59, 60, 61, 62, 63, 57, 58, 59, 60, 61, 62, 63, 57, 58, 59, 60, 61, 62, 57, 58, 59, 60, 61, 62, 63, 62, 63, -1, -1, -1, -1, -1, -1, -1, -1, -1, -1, -1, -1, -1, -1, -1, 17, 18, 19, 20, 21, 22, 23, -1, 17, 18, 19, 20, 21, 22, 23, 58, 59, 60, 61, 62, 63, 57, 58, 59, 60, 61, 62, 63, -1, -1, -1, -1, -1, -1, -1, -1, -1, -1, -1, -1, -1, -1, -1, -1, -1, -1, -1, -1, -1, -1, -1, -1, -1, -1, -1, -1, -1, 57, 58, 59, 60, 61, 62, 63, -1, -1, -1, -1, -1, -1, -1, -1, 17, 18, 19, 20, 21, 22, 23, -1, 25, 26, 27, 28, 29, 30, 31, 17, 25, 26, 27, 28, 29, 30, 31, 17, 18, 19, 20, 21, 22, 23, -1, -1, -1, -1, -1, -1, -1, 17, 18, 19, 20, 21, 22, 23, 17, 18, 19, 20, 21, 17, 18, 19, 20, 21, 22, 23, 17, 18, 19, 20, 21, 22, 23, 18, 19, 20, 21, 22, 23, -1, -1, -1, -1, -1, -1, -1, -1, -1, -1, -1, 25, 26, 27, 28, 29, 30, 31, -1, 33, 34, 35, 36, 37, 38, 39, 25, 33, 34, 35, 36, 37, 38, 39, 25, 26, 27, 28, 29, 30, 31, 17, 18, 19, 20, 21, 22, 23, 25, 26, 27, 28, 29, 30, 31, 25, 26, 27, 28, 29, 25, 26, 27, 28, 29, 30, 31, 25, 26, 27, 28, 29, 30, 31, 17, 18, 19, 20, 21, 22, 23, -1, -1, -1, -1, -1, -1, -1, -1, -1, -1, 33, 34, 35, 36, 37, 38, 39, -1, 41, 42, 43, 44, 45, 46, 47, 33, 41, 42, 43, 44, 45, 46, 47, 33, 34, 35, 36, 37, 38, 39, 25, 26, 27, 28, 29, 30, 31, 33, 34, 35, 36, 37, 38, 39, 33, 34, 35, 36, 37, 33, 34, 35, 36, 37, 38, 39, 33, 34, 35, 36, 37, 38, 39, 25, 26, 27, 28, 29, 30, 31, -1, -1, -1, -1, -1, -1, -1, -1, -1, -1, 41, 42, 43, 44, 45, 46, 47, -1, 49, 50, 51, 52, 53, 54, 55, 41, 49, 50, 51, 52, 53, 54, 55, 41, 42, 43, 44, 45, 46, 47, 33, 34, 35, 36, 37, 38, 39, 41, 42, 43, 44, 45, 46, 47, 41, 42, 43, 44, 45, 41, 42, 43, 44, 45, 46, 47, 41, 42, 43, 44, 45, 46, 47, 33, 34, 35, 36, 37, 38, 39, -1, -1, -1, -1, -1, -1, -1, -1, -1, -1, 49, 50, 51, 52, 53, 54, 55, -1, 57, 58, 59, 60, 61, 62, 63, 49, 57, 58, 59, 60, 61, 62, 63, 49, 50, 51, 52, 53, 54, 55, 41, 42, 43, 44, 45, 46, 47, 49, 50, 51, 52, 53, 54, 55, 49, 50, 51, 52, 53, 49, 50, 51, 52, 53, 54, 55, 49, 50, 51, 52, 53, 54, 55, 41, 42, 43, 44, 45, 46, 47, -1, -1, -1, -1, -1, -1, -1, -1, -1, -1, 17, 18, 19, 20, 21, 22, 23, -1, 49, 50, 57, 58, 59, 60, 61, 57, 58, 59, 60, 61, 62, 63, -1, 17, 18, 19, 20, 21, 22, 23, 17, 18, 19, 20, 21, 22, 23, 17, 18, 19, 20, 21, 22, 23, 17, 18, 19, 20, 21, 57, 58, 59, 60, 61, 62, 63, 57, 58, 59, 60, 61, 62, 63, 49, 50, 51, 52, 53, 54, 55, -1, -1, -1, -1, -1, -1, -1, -1, -1, -1, 25, 26, 27, 28, 29, 30, 31, -1, 57, 58, 59, 60, 61, 62, 63, 39, 26, 27, 28, 29, 30, 31, -1, 25, 26, 27, 28, 29, 30, 31, 25, 26, 27, 28, 29, 30, 31, 25, 26, 27, 28, 29, 30, 31, 25, 26, 27, 28, 29, 49, 50, 51, 52, 53, 54, 55, 57, 58, 59, 60, 61, 62, 63, 57, 58, 59, 60, 61, 62, 63, -1, -1, -1, -1, -1, -1, -1, -1, -1, -1, 33, 34, 35, 36, 37, 38, 39, -1, 25, 41, 42, 43, 44, 45, 46, 47, 34, 35, 36, 37, 38, 39, -1, 17, 18, 19, 20, 21, 22, 23, 33, 34, 35, 36, 37, 38, 39, 33, 34, 35, 36, 37, 38, 39, 33, 34, 35, 36, 37, 57, 58, 59, 60, 61, 62, 63, 38, 39, 57, 58, 59, 60, 61, 62, 63, 28, 29, 30, 31, -1, -1, -1, -1, -1, -1, -1, -1, -1, -1, -1, 41, 42, 43, 44, 45, 46, 47, -1, 33, 49, 50, 51, 52, 53, 54, 55, 42, 43, 44, 45, 46, 47, -1, 25, 26, 27, 28, 29, 30, 31, 41, 42, 43, 44, 45, 46, 47, 41, 42, 43, 44, 45, 46, 47, 17, 18, 19, 20, 21, 22, 23, 41, 42, 43, 44, 45, 46, 47, 20, 21, 22, 23, 33, 34, 35, 36, 37, 38, 39, -1, -1, -1, -1, -1, -1, -1, -1, -1, -1, -1, 49, 50, 51, 52, 53, 54, 55, -1, 41, 57, 58, 59, 60, 61, 62, 63, 50, 51, 52, 53, 54, 55, -1, 33, 34, 35, 36, 37, 38, 39, 49, 50, 51, 52, 53, 54, 55, 49, 50, 51, 52, 53, 54, 55, 25, 26, 27, 28, 29, 30, 31, 49, 50, 51, 52, 53, 54, 55, 28, 29, 30, 31, 41, 42, 43, 44, 45, 46, 47, -1, -1, -1, -1, -1, -1, -1, -1, -1, -1, -1, 57, 58, 59, 60, 17, 18, 19, 20, 21, 22, 23, 17, 18, 19, 20, 21, 22, 23, 17, 18, 19, 20, 21, 22, 23, 17, 18, 19, 20, 21, 22, 23, 17, 18, 19, 20, 21, 22, 23, 17, 18, 19, 20, 21, 22, 23, 17, 18, 19, 20, 21, 22, 23, 59, 60, 61, 62, 63, 36, 37, 38, 39, 49, 50, 51, 52, 53, 54, 55, -1, -1, -1, -1, -1, -1, -1, -1, -1, 17, 18, 19, 20, 21, 22, 25, 26, 27, 28, 29, 30, 31, 25, 26, 27, 28, 29, 30, 31, 25, 26, 27, 28, 29, 30, 31, 25, 26, 27, 28, 29, 30, 31, 25, 26, 27, 28, 29, 30, 31, 25, 26, 27, 28, 29, 30, 31, 25, 26, 27, 28, 29, 30, 31, 17, 18, 19, 20, 21, 22, 23, 17, 18, 19, 20, 21, 22, 23, 62, 63, -1, -1, -1, -1, -1],
      "exportMode": 0,
      "arrayMode": 0
    }
  ]
}